nba_data_miner/__init__.py
nba_data_miner/compare.py
nba_data_miner/helper_functions.py
nba_data_miner/search.py
nba_data_miner-0.1.0.dist-info/LICENSE
nba_data_miner-0.1.0.dist-info/WHEEL
nba_data_miner-0.1.0.dist-info/METADATA
nba_data_miner-0.1.0.dist-info/RECORD
